sfquery/__init__.py
sfquery/interface.py
sfquery/sfquery.py
sfquery-1.0.0.dist-info/METADATA
sfquery-1.0.0.dist-info/RECORD
sfquery-1.0.0.dist-info/WHEEL
sfquery-1.0.0.dist-info/top_level.txt
