Metadata-Version: 2.1
Name: sfquery
Version: 1.0.0
Summary: A package to query reliable collections using python or jupyter notebook interfaces
Home-page: https://github.com/amenarde/reliable-collections-cli
Author: Antonio Menarde, Shalabh Mohan Shrivastava
Author-email: amenarde@gmail.com
License: MIT
Platform: UNKNOWN
Classifier: Development Status :: 3 - Alpha
Classifier: Intended Audience :: Developers
Classifier: Topic :: Software Development :: Build Tools
Classifier: Environment :: Console
Classifier: License :: OSI Approved :: MIT License
Classifier: Natural Language :: English
Classifier: Programming Language :: Python :: 2.7
Classifier: Programming Language :: Python :: 3.5
Classifier: Programming Language :: Python :: 3.6
Requires-Dist: xmljson
Requires-Dist: sfctl
Requires-Dist: ipywidgets
